dgo/__init__.py
dgo/cli.py
dgo/dgo.py
dgo-0.6.6.dist-info/AUTHORS.rst
dgo-0.6.6.dist-info/LICENSE
dgo-0.6.6.dist-info/METADATA
dgo-0.6.6.dist-info/WHEEL
dgo-0.6.6.dist-info/entry_points.txt
dgo-0.6.6.dist-info/top_level.txt
dgo-0.6.6.dist-info/RECORD
