Metadata-Version: 2.1
Name: dgo
Version: 0.6.6
Summary: Shortcut cmds collection.
Home-page: https://github.com/daimon99/dgo
Author: Jian Dai
Author-email: daijian1@qq.com
License: MIT license
Keywords: dgo
Platform: UNKNOWN
Classifier: Development Status :: 2 - Pre-Alpha
Classifier: Intended Audience :: Developers
Classifier: License :: OSI Approved :: MIT License
Classifier: Natural Language :: English
Classifier: Programming Language :: Python :: 2
Classifier: Programming Language :: Python :: 2.6
Classifier: Programming Language :: Python :: 2.7
Classifier: Programming Language :: Python :: 3
Classifier: Programming Language :: Python :: 3.6
Classifier: Programming Language :: Python :: 3.7
Classifier: Programming Language :: Python :: 3.8
Requires-Python: >=2.6
Requires-Dist: Click (==6.6)
Requires-Dist: requests
